{
    "status": "ok",
    "data": {
        "user": {
            "edge_follow": {
                "page_info": {
                    "has_next_page": false,
                    "end_cursor": "AQBRIGYF0oKSdT_qcHT6ppFzvcZhb8FgpVttAsYnvUsSpHe3yAJiajHKDps6iL3KelA"
                },
                "count": 884,
                "edges": [
                    {
                        "node": {
                            "is_verified": false,
                            "id": "30657199",
                            "followed_by_viewer": false,
                            "username": "parkncube",
                            "requested_by_viewer": false,
                            "profile_pic_url": "https://scontent-icn1-1.cdninstagram.com/t51.2885-19/s150x150/18512713_257273138074976_7553877171832356864_a.jpg",
                            "full_name": "Shini Park"
                        }
                    },
                    {
                        "node": {
                            "is_verified": true,
                            "id": "10365980",
                            "followed_by_viewer": false,
                            "username": "thehautepursuit",
                            "requested_by_viewer": false,
                            "profile_pic_url": "https://scontent-icn1-1.cdninstagram.com/t51.2885-19/s150x150/11821671_377522032445829_1586696110_a.jpg",
                            "full_name": "Vanessa Hong"
                        }
                    },
                    {
                        "node": {
                            "is_verified": true,
                            "id": "19769622",
                            "followed_by_viewer": false,
                            "username": "chiaraferragni",
                            "requested_by_viewer": false,
                            "profile_pic_url": "https://scontent-icn1-1.cdninstagram.com/t51.2885-19/s150x150/16585671_413621785647765_4894079104527106048_a.jpg",
                            "full_name": "Chiara Ferragni"
                        }
                    },
                    {
                        "node": {
                            "is_verified": false,
                            "id": "14456584",
                            "followed_by_viewer": false,
                            "username": "karla_deras",
                            "requested_by_viewer": false,
                            "profile_pic_url": "https://scontent-icn1-1.cdninstagram.com/t51.2885-19/11230359_820104268074143_139137147_a.jpg",
                            "full_name": "karla_deras"
                        }
                    },
                    {
                        "node": {
                            "is_verified": true,
                            "id": "3119358",
                            "followed_by_viewer": false,
                            "username": "nylonmag",
                            "requested_by_viewer": false,
                            "profile_pic_url": "https://scontent-icn1-1.cdninstagram.com/t51.2885-19/s150x150/17075951_1855530908067906_2419007554853011456_a.jpg",
                            "full_name": "Nylon Magazine"
                        }
                    },
                    {
                        "node": {
                            "is_verified": false,
                            "id": "177582211",
                            "followed_by_viewer": false,
                            "username": "chelseadunstan",
                            "requested_by_viewer": false,
                            "profile_pic_url": "https://scontent-icn1-1.cdninstagram.com/t51.2885-19/s150x150/12269808_182484842095054_1674878929_a.jpg",
                            "full_name": "Chelsea Dunstan"
                        }
                    },
                    {
                        "node": {
                            "is_verified": true,
                            "id": "9677692",
                            "followed_by_viewer": false,
                            "username": "smashleybell",
                            "requested_by_viewer": false,
                            "profile_pic_url": "https://scontent-icn1-1.cdninstagram.com/t51.2885-19/s150x150/14574018_1209074832508895_3003805031951499264_a.jpg",
                            "full_name": "Ashley Madekwe"
                        }
                    },
                    {
                        "node": {
                            "is_verified": false,
                            "id": "8138529",
                            "followed_by_viewer": false,
                            "username": "froufrouu",
                            "requested_by_viewer": false,
                            "profile_pic_url": "https://scontent-icn1-1.cdninstagram.com/t51.2885-19/1391328_100908646907620_973478421_a.jpg",
                            "full_name": "Nadia Sarwar"
                        }
                    },
                    {
                        "node": {
                            "is_verified": true,
                            "id": "1860612",
                            "followed_by_viewer": false,
                            "username": "stylescrapbook",
                            "requested_by_viewer": false,
                            "profile_pic_url": "https://scontent-icn1-1.cdninstagram.com/t51.2885-19/s150x150/17333579_456810068043676_2009034093018218496_a.jpg",
                            "full_name": "\uff21\uff2e\uff24\uff39  \uff34\uff2f\uff32\uff32\uff25\uff33"
                        }
                    },
                    {
                        "node": {
                            "is_verified": false,
                            "id": "30468376",
                            "followed_by_viewer": false,
                            "username": "cocorosas",
                            "requested_by_viewer": false,
                            "profile_pic_url": "https://scontent-icn1-1.cdninstagram.com/t51.2885-19/s150x150/12749877_652217841583189_1088616213_a.jpg",
                            "full_name": "Chantal Galda (cocorosa)"
                        }
                    },
                    {
                        "node": {
                            "is_verified": false,
                            "id": "5890342",
                            "followed_by_viewer": false,
                            "username": "theglamourai",
                            "requested_by_viewer": false,
                            "profile_pic_url": "https://scontent-icn1-1.cdninstagram.com/t51.2885-19/s150x150/17596214_433824736952918_8575061051534475264_a.jpg",
                            "full_name": "Kelly Framel"
                        }
                    },
                    {
                        "node": {
                            "is_verified": true,
                            "id": "6913295",
                            "followed_by_viewer": false,
                            "username": "garypeppergirl",
                            "requested_by_viewer": false,
                            "profile_pic_url": "https://scontent-icn1-1.cdninstagram.com/t51.2885-19/s150x150/13108539_1701583913436862_84078897_a.jpg",
                            "full_name": "Nicole Warne"
                        }
                    },
                    {
                        "node": {
                            "is_verified": false,
                            "id": "10685920",
                            "followed_by_viewer": false,
                            "username": "georgietomich",
                            "requested_by_viewer": false,
                            "profile_pic_url": "https://scontent-icn1-1.cdninstagram.com/t51.2885-19/11939652_411915385673259_1504093991_a.jpg",
                            "full_name": "Georgie Tomich"
                        }
                    },
                    {
                        "node": {
                            "is_verified": false,
                            "id": "33054444",
                            "followed_by_viewer": false,
                            "username": "_f.e.d.i_",
                            "requested_by_viewer": false,
                            "profile_pic_url": "https://scontent-icn1-1.cdninstagram.com/t51.2885-19/s150x150/12277363_1524987374478113_362987108_a.jpg",
                            "full_name": "Fedi"
                        }
                    },
                    {
                        "node": {
                            "is_verified": false,
                            "id": "6297230",
                            "followed_by_viewer": false,
                            "username": "emiliesobels",
                            "requested_by_viewer": false,
                            "profile_pic_url": "https://scontent-icn1-1.cdninstagram.com/t51.2885-19/s150x150/14288194_102052456926990_1669257830072320000_a.jpg",
                            "full_name": "EMILIE SOBELS"
                        }
                    },
                    {
                        "node": {
                            "is_verified": false,
                            "id": "9680343",
                            "followed_by_viewer": false,
                            "username": "anafortunato",
                            "requested_by_viewer": false,
                            "profile_pic_url": "https://scontent-icn1-1.cdninstagram.com/t51.2885-19/s150x150/18253270_668753709983776_8457049918769463296_a.jpg",
                            "full_name": "Ana Fortunato"
                        }
                    }
                ]
            }
        }
    }
}