{
    "status": "ok",
    "data": {
        "user": {
            "edge_follow": {
                "count": 2069,
                "page_info": {
                    "has_next_page": true,
                    "end_cursor": "AQDTC9xp58J7iT_uSi95hnelaNx234bVs1NRm2k2FGAFO3hhNLOciag0srCu3-sc7tVY7IwykAPqXL56ehD7TPpAWjhD0ZsSXF6NNn7ZNLU6ag"
                },
                "edges": [
                    {
                        "node": {
                            "profile_pic_url": "https://scontent-icn1-1.cdninstagram.com/t51.2885-19/929235_886050584741440_712848219_a.jpg",
                            "id": "267785833",
                            "username": "striketwoposes",
                            "followed_by_viewer": false,
                            "is_verified": false,
                            "requested_by_viewer": false,
                            "full_name": "Strike2Poses"
                        }
                    },
                    {
                        "node": {
                            "profile_pic_url": "https://scontent-icn1-1.cdninstagram.com/t51.2885-19/s150x150/17076372_1853202434953257_2244604729852166144_a.jpg",
                            "id": "13641413",
                            "username": "mikewillmadeit",
                            "followed_by_viewer": false,
                            "is_verified": true,
                            "requested_by_viewer": false,
                            "full_name": "Mike WiLL Made It"
                        }
                    },
                    {
                        "node": {
                            "profile_pic_url": "https://scontent-icn1-1.cdninstagram.com/t51.2885-19/s150x150/12558358_1962849187272829_1512968624_a.jpg",
                            "id": "46776882",
                            "username": "robertcavalli",
                            "followed_by_viewer": false,
                            "is_verified": true,
                            "requested_by_viewer": false,
                            "full_name": "Robert Cavalli"
                        }
                    },
                    {
                        "node": {
                            "profile_pic_url": "https://scontent-icn1-1.cdninstagram.com/t51.2885-19/s150x150/18014010_1951263798484637_928885968813948928_a.jpg",
                            "id": "633403688",
                            "username": "justcavallimilano",
                            "followed_by_viewer": false,
                            "is_verified": false,
                            "requested_by_viewer": false,
                            "full_name": "JustCavalliMilano"
                        }
                    },
                    {
                        "node": {
                            "profile_pic_url": "https://scontent-icn1-1.cdninstagram.com/t51.2885-19/10362131_444631439026660_1290915534_a.jpg",
                            "id": "12339576",
                            "username": "robertocavalli",
                            "followed_by_viewer": false,
                            "is_verified": false,
                            "requested_by_viewer": false,
                            "full_name": "Roberto Cavalli Official"
                        }
                    },
                    {
                        "node": {
                            "profile_pic_url": "https://scontent-icn1-1.cdninstagram.com/t51.2885-19/s150x150/17126653_1857886054427020_1292179862060007424_a.jpg",
                            "id": "444524585",
                            "username": "luxecartel",
                            "followed_by_viewer": false,
                            "is_verified": false,
                            "requested_by_viewer": false,
                            "full_name": "L U X E  C A R T E L"
                        }
                    },
                    {
                        "node": {
                            "profile_pic_url": "https://scontent-icn1-1.cdninstagram.com/t51.2885-19/11850277_1480374335595967_87586841_a.jpg",
                            "id": "613509366",
                            "username": "martingrantofficial",
                            "followed_by_viewer": false,
                            "is_verified": false,
                            "requested_by_viewer": false,
                            "full_name": "Martin Grant Official"
                        }
                    },
                    {
                        "node": {
                            "profile_pic_url": "https://scontent-icn1-1.cdninstagram.com/t51.2885-19/11348170_137218836615511_1349200976_a.jpg",
                            "id": "374096064",
                            "username": "carlynecerfdedudzeele",
                            "followed_by_viewer": false,
                            "is_verified": true,
                            "requested_by_viewer": false,
                            "full_name": "carlynecerfdedudzeele #CCD"
                        }
                    },
                    {
                        "node": {
                            "profile_pic_url": "https://scontent-icn1-1.cdninstagram.com/t51.2885-19/11249601_710109939092976_824127928_a.jpg",
                            "id": "484683815",
                            "username": "oribecanales",
                            "followed_by_viewer": false,
                            "is_verified": false,
                            "requested_by_viewer": false,
                            "full_name": "ORIBE__________________canales"
                        }
                    },
                    {
                        "node": {
                            "profile_pic_url": "https://scontent-icn1-1.cdninstagram.com/t51.2885-19/s150x150/15276758_1742311819425051_3123716653385252864_a.jpg",
                            "id": "23799578",
                            "username": "i_am_other",
                            "followed_by_viewer": false,
                            "is_verified": true,
                            "requested_by_viewer": false,
                            "full_name": "i am OTHER"
                        }
                    },
                    {
                        "node": {
                            "profile_pic_url": "https://scontent-icn1-1.cdninstagram.com/t51.2885-19/s150x150/17077201_394319597601915_5210021026284437504_a.jpg",
                            "id": "180261276",
                            "username": "valemicchetti",
                            "followed_by_viewer": false,
                            "is_verified": false,
                            "requested_by_viewer": false,
                            "full_name": "Valentina Micchetti"
                        }
                    },
                    {
                        "node": {
                            "profile_pic_url": "https://scontent-icn1-1.cdninstagram.com/t51.2885-19/s150x150/15275518_1041794115947529_4807850257306091520_a.jpg",
                            "id": "19113152",
                            "username": "barrefaeli",
                            "followed_by_viewer": false,
                            "is_verified": true,
                            "requested_by_viewer": false,
                            "full_name": "Bar Refaeli"
                        }
                    },
                    {
                        "node": {
                            "profile_pic_url": "https://scontent-icn1-1.cdninstagram.com/t51.2885-19/s150x150/18381881_1602635229756096_1334552196926144512_a.jpg",
                            "id": "205872163",
                            "username": "ellechina",
                            "followed_by_viewer": false,
                            "is_verified": false,
                            "requested_by_viewer": false,
                            "full_name": "ELLE CHINA"
                        }
                    },
                    {
                        "node": {
                            "profile_pic_url": "https://scontent-icn1-1.cdninstagram.com/t51.2885-19/s150x150/17333038_216447922166541_7851572401774002176_a.jpg",
                            "id": "758993636",
                            "username": "bartolistyle",
                            "followed_by_viewer": false,
                            "is_verified": false,
                            "requested_by_viewer": false,
                            "full_name": "Marie-Lou Bartoli"
                        }
                    },
                    {
                        "node": {
                            "profile_pic_url": "https://scontent-icn1-1.cdninstagram.com/t51.2885-19/10958648_509347352541479_1515494886_a.jpg",
                            "id": "20949707",
                            "username": "katiecouric",
                            "followed_by_viewer": false,
                            "is_verified": true,
                            "requested_by_viewer": false,
                            "full_name": "Katie Couric"
                        }
                    },
                    {
                        "node": {
                            "profile_pic_url": "https://scontent-icn1-1.cdninstagram.com/t51.2885-19/10570038_1539956726225375_723144734_a.jpg",
                            "id": "10723800",
                            "username": "mikoh",
                            "followed_by_viewer": false,
                            "is_verified": true,
                            "requested_by_viewer": false,
                            "full_name": "MIKOH"
                        }
                    },
                    {
                        "node": {
                            "profile_pic_url": "https://scontent-icn1-1.cdninstagram.com/t51.2885-19/s150x150/14723102_1126460810761373_5657617237696053248_a.jpg",
                            "id": "181481629",
                            "username": "marthastewart",
                            "followed_by_viewer": false,
                            "is_verified": true,
                            "requested_by_viewer": false,
                            "full_name": "Martha Stewart"
                        }
                    },
                    {
                        "node": {
                            "profile_pic_url": "https://scontent-icn1-1.cdninstagram.com/t51.2885-19/s150x150/14474282_117908562006669_8834654591506186240_a.jpg",
                            "id": "279823419",
                            "username": "atelierromy",
                            "followed_by_viewer": false,
                            "is_verified": false,
                            "requested_by_viewer": false,
                            "full_name": "Atelier Romy"
                        }
                    },
                    {
                        "node": {
                            "profile_pic_url": "https://scontent-icn1-1.cdninstagram.com/t51.2885-19/s150x150/12547494_1659099561017614_1449940753_a.jpg",
                            "id": "281087348",
                            "username": "therealpumpyjackson",
                            "followed_by_viewer": false,
                            "is_verified": false,
                            "requested_by_viewer": false,
                            "full_name": "Amber Clayton"
                        }
                    }
                ]
            }
        }
    }
}