{
    "status": "ok",
    "data": {
        "user": {
            "edge_follow": {
                "count": 130235,
                "page_info": {
                    "has_next_page": true,
                    "end_cursor": "AQBhtWqPkbOP7OoqyITuQJhl1-D-etCQqB3AicE3SOdDyPPoJTaX2jOCJQV0uCmfzRai7oKMTKRwYf-MGEuveVGjK5KzXtZRL5kpsAD-9Xhd1g"
                },
                "edges": [
                    {
                        "node": {
                            "profile_pic_url": "https://scontent-icn1-1.cdninstagram.com/t51.2885-19/10431852_283946788445048_379173649_a.jpg",
                            "id": "33753525",
                            "username": "thatgirlfatima",
                            "followed_by_viewer": false,
                            "is_verified": false,
                            "requested_by_viewer": false,
                            "full_name": ""
                        }
                    },
                    {
                        "node": {
                            "profile_pic_url": "https://scontent-icn1-1.cdninstagram.com/t51.2885-19/11355973_300413293462245_1109922072_a.jpg",
                            "id": "42503799",
                            "username": "boopiefbebe",
                            "followed_by_viewer": false,
                            "is_verified": false,
                            "requested_by_viewer": false,
                            "full_name": "Dee Langi"
                        }
                    },
                    {
                        "node": {
                            "profile_pic_url": "https://scontent-icn1-1.cdninstagram.com/t51.2885-19/s150x150/15099612_772336236252817_1770568141420625920_a.jpg",
                            "id": "19359567",
                            "username": "eveeherrera",
                            "followed_by_viewer": false,
                            "is_verified": false,
                            "requested_by_viewer": false,
                            "full_name": "Eve Herreraa"
                        }
                    },
                    {
                        "node": {
                            "profile_pic_url": "https://scontent-icn1-1.cdninstagram.com/t51.2885-19/s150x150/14487453_327182210990796_2724400792118231040_a.jpg",
                            "id": "16630779",
                            "username": "__melodious__",
                            "followed_by_viewer": false,
                            "is_verified": false,
                            "requested_by_viewer": false,
                            "full_name": "Aria Harris"
                        }
                    },
                    {
                        "node": {
                            "profile_pic_url": "https://scontent-icn1-1.cdninstagram.com/t51.2885-19/s150x150/17267954_267274333726438_160365183955369984_a.jpg",
                            "id": "14674985",
                            "username": "kathleencoveno",
                            "followed_by_viewer": false,
                            "is_verified": false,
                            "requested_by_viewer": false,
                            "full_name": "Kathleen Coveno"
                        }
                    },
                    {
                        "node": {
                            "profile_pic_url": "https://scontent-icn1-1.cdninstagram.com/t51.2885-19/s150x150/13320025_1085156228232071_1451051731_a.jpg",
                            "id": "22487824",
                            "username": "sophieallen99",
                            "followed_by_viewer": false,
                            "is_verified": false,
                            "requested_by_viewer": false,
                            "full_name": "Sophie Allen"
                        }
                    },
                    {
                        "node": {
                            "profile_pic_url": "https://scontent-icn1-1.cdninstagram.com/t51.2885-19/s150x150/17662698_724800957727075_2493536889684885504_a.jpg",
                            "id": "3972488",
                            "username": "uve_de_eva",
                            "followed_by_viewer": false,
                            "is_verified": false,
                            "requested_by_viewer": false,
                            "full_name": "UvE"
                        }
                    },
                    {
                        "node": {
                            "profile_pic_url": "https://scontent-icn1-1.cdninstagram.com/t51.2885-19/s150x150/14677342_890719107696741_3274378084584783872_a.jpg",
                            "id": "12593174",
                            "username": "alex_accetta",
                            "followed_by_viewer": false,
                            "is_verified": false,
                            "requested_by_viewer": false,
                            "full_name": "Alex Accetta"
                        }
                    },
                    {
                        "node": {
                            "profile_pic_url": "https://scontent-icn1-1.cdninstagram.com/t51.2885-19/s150x150/15034743_1711571285824624_3563950556412116992_a.jpg",
                            "id": "27915625",
                            "username": "melissahalliwell",
                            "followed_by_viewer": false,
                            "is_verified": false,
                            "requested_by_viewer": false,
                            "full_name": ""
                        }
                    },
                    {
                        "node": {
                            "profile_pic_url": "https://scontent-icn1-1.cdninstagram.com/t51.2885-19/s150x150/17076731_109478829550176_2928864990871945216_a.jpg",
                            "id": "17142758",
                            "username": "jessie_doucette",
                            "followed_by_viewer": false,
                            "is_verified": false,
                            "requested_by_viewer": false,
                            "full_name": "Jessie Doucette"
                        }
                    },
                    {
                        "node": {
                            "profile_pic_url": "https://scontent-icn1-1.cdninstagram.com/t51.2885-19/s150x150/13743123_1768884886725448_1410961546_a.jpg",
                            "id": "16796382",
                            "username": "racchiieey",
                            "followed_by_viewer": false,
                            "is_verified": false,
                            "requested_by_viewer": false,
                            "full_name": "Rachel Richelle"
                        }
                    },
                    {
                        "node": {
                            "profile_pic_url": "https://scontent-icn1-1.cdninstagram.com/t51.2885-19/10508080_1429919983960283_1448649342_a.jpg",
                            "id": "29415341",
                            "username": "hanlink23",
                            "followed_by_viewer": false,
                            "is_verified": false,
                            "requested_by_viewer": false,
                            "full_name": "HannahELink"
                        }
                    },
                    {
                        "node": {
                            "profile_pic_url": "https://scontent-icn1-1.cdninstagram.com/t51.2885-19/11348294_884991901585229_268813240_a.jpg",
                            "id": "29927295",
                            "username": "animalgirl8",
                            "followed_by_viewer": false,
                            "is_verified": false,
                            "requested_by_viewer": false,
                            "full_name": "Zoe Loos"
                        }
                    },
                    {
                        "node": {
                            "profile_pic_url": "https://scontent-icn1-1.cdninstagram.com/t51.2885-19/s150x150/18443724_252871678514918_69909809742217216_a.jpg",
                            "id": "26646450",
                            "username": "bradie_7",
                            "followed_by_viewer": false,
                            "is_verified": false,
                            "requested_by_viewer": false,
                            "full_name": "Bradie Pillman"
                        }
                    },
                    {
                        "node": {
                            "profile_pic_url": "https://scontent-icn1-1.cdninstagram.com/t51.2885-19/s150x150/18513270_264004837340658_4530251110622953472_a.jpg",
                            "id": "27420804",
                            "username": "samantha_christian44",
                            "followed_by_viewer": false,
                            "is_verified": false,
                            "requested_by_viewer": false,
                            "full_name": "samantha"
                        }
                    },
                    {
                        "node": {
                            "profile_pic_url": "https://scontent-icn1-1.cdninstagram.com/t51.2885-19/s150x150/18513675_1520748537958766_6822722220196888576_a.jpg",
                            "id": "34534362",
                            "username": "dandra_dunbar",
                            "followed_by_viewer": false,
                            "is_verified": false,
                            "requested_by_viewer": false,
                            "full_name": "dandra\u2600\ufe0f"
                        }
                    },
                    {
                        "node": {
                            "profile_pic_url": "https://scontent-icn1-1.cdninstagram.com/t51.2885-19/s150x150/17932199_832823303531982_3642262318617722880_a.jpg",
                            "id": "16648387",
                            "username": "morganvandoren",
                            "followed_by_viewer": false,
                            "is_verified": false,
                            "requested_by_viewer": false,
                            "full_name": "Morgan VanDoren"
                        }
                    },
                    {
                        "node": {
                            "profile_pic_url": "https://scontent-icn1-1.cdninstagram.com/t51.2885-19/s150x150/14099449_1727077517615784_1775336144_a.jpg",
                            "id": "15038277",
                            "username": "ronjaanderzzon",
                            "followed_by_viewer": false,
                            "is_verified": false,
                            "requested_by_viewer": false,
                            "full_name": "Ronja Andersson \ud83d\udc96"
                        }
                    }
                ]
            }
        }
    }
}