{
    "data": {
        "user": {
            "edge_follow": {
                "page_info": {
                    "has_next_page": true,
                    "end_cursor": "AQCeCiBrvuSWM7g6GpigkPbFIqc_fm3VE19ZpC9rdwuIjbHGGgq07Yr99P-Xr1ngd7INY__dt1yMXHUo-tjVNdOym1rbm87p8tVgSAxp-IzDOQ"
                },
                "edges": [
                    {
                        "node": {
                            "followed_by_viewer": false,
                            "full_name": "London Style Calling",
                            "username": "london_style_calling",
                            "requested_by_viewer": false,
                            "is_verified": false,
                            "id": "2246842233",
                            "profile_pic_url": "https://scontent-icn1-1.cdninstagram.com/t51.2885-19/s150x150/12142373_1707137526172206_609086150_a.jpg"
                        }
                    },
                    {
                        "node": {
                            "followed_by_viewer": false,
                            "full_name": "Lena Perminova",
                            "username": "lenaperminova",
                            "requested_by_viewer": false,
                            "is_verified": true,
                            "id": "178170399",
                            "profile_pic_url": "https://scontent-icn1-1.cdninstagram.com/t51.2885-19/s150x150/16229481_174688576351835_5896794259784204288_a.jpg"
                        }
                    },
                    {
                        "node": {
                            "followed_by_viewer": false,
                            "full_name": "",
                            "username": "miss.lendel",
                            "requested_by_viewer": false,
                            "is_verified": false,
                            "id": "267902674",
                            "profile_pic_url": "https://scontent-icn1-1.cdninstagram.com/t51.2885-19/s150x150/15253352_232007337232389_2200837381018353664_a.jpg"
                        }
                    },
                    {
                        "node": {
                            "followed_by_viewer": false,
                            "full_name": "Mary Orton",
                            "username": "maryorton",
                            "requested_by_viewer": false,
                            "is_verified": true,
                            "id": "305778076",
                            "profile_pic_url": "https://scontent-icn1-1.cdninstagram.com/t51.2885-19/s150x150/17494743_804113126431744_2216975785057583104_a.jpg"
                        }
                    },
                    {
                        "node": {
                            "followed_by_viewer": false,
                            "full_name": "Neiman Marcus",
                            "username": "neimanmarcus",
                            "requested_by_viewer": false,
                            "is_verified": true,
                            "id": "3907894",
                            "profile_pic_url": "https://scontent-icn1-1.cdninstagram.com/t51.2885-19/11324955_1622470184701472_1302564374_a.jpg"
                        }
                    },
                    {
                        "node": {
                            "followed_by_viewer": false,
                            "full_name": "Michelle Madsen",
                            "username": "michelletakeaim",
                            "requested_by_viewer": false,
                            "is_verified": false,
                            "id": "2408805",
                            "profile_pic_url": "https://scontent-icn1-1.cdninstagram.com/t51.2885-19/s150x150/14482895_1283473235006216_9047258582214508544_a.jpg"
                        }
                    },
                    {
                        "node": {
                            "followed_by_viewer": false,
                            "full_name": "Mich\u00e8le Kr\u00fcsi",
                            "username": "thefashionfraction",
                            "requested_by_viewer": false,
                            "is_verified": false,
                            "id": "318176614",
                            "profile_pic_url": "https://scontent-icn1-1.cdninstagram.com/t51.2885-19/s150x150/17882518_1428992427166178_8044911531424481280_a.jpg"
                        }
                    },
                    {
                        "node": {
                            "followed_by_viewer": false,
                            "full_name": "ROSA CRESPO | NYC Blogger",
                            "username": "rosacrespo",
                            "requested_by_viewer": false,
                            "is_verified": false,
                            "id": "29404653",
                            "profile_pic_url": "https://scontent-icn1-1.cdninstagram.com/t51.2885-19/s150x150/17125764_1950353745232228_2557812750306770944_a.jpg"
                        }
                    },
                    {
                        "node": {
                            "followed_by_viewer": false,
                            "full_name": "Ines Klara Beauty",
                            "username": "inesklarabeauty",
                            "requested_by_viewer": false,
                            "is_verified": false,
                            "id": "2965366868",
                            "profile_pic_url": "https://scontent-icn1-1.cdninstagram.com/t51.2885-19/s150x150/10269004_948747068536485_2047501503_a.jpg"
                        }
                    },
                    {
                        "node": {
                            "followed_by_viewer": false,
                            "full_name": "\u2764Bota Balabekova\u2764",
                            "username": "bota_070",
                            "requested_by_viewer": false,
                            "is_verified": false,
                            "id": "490135730",
                            "profile_pic_url": "https://scontent-icn1-1.cdninstagram.com/t51.2885-19/s150x150/18443483_512146669176475_6266562360962449408_a.jpg"
                        }
                    },
                    {
                        "node": {
                            "followed_by_viewer": false,
                            "full_name": "LILIYA and TAYA",
                            "username": "taya_gvo",
                            "requested_by_viewer": false,
                            "is_verified": false,
                            "id": "1931047409",
                            "profile_pic_url": "https://scontent-icn1-1.cdninstagram.com/t51.2885-19/s150x150/18443693_1363616497079435_565713816415895552_a.jpg"
                        }
                    },
                    {
                        "node": {
                            "followed_by_viewer": false,
                            "full_name": "Wildlife Planet",
                            "username": "wildlifeplanet",
                            "requested_by_viewer": false,
                            "is_verified": false,
                            "id": "1295347780",
                            "profile_pic_url": "https://scontent-icn1-1.cdninstagram.com/t51.2885-19/11142997_968647096480093_322585884_a.jpg"
                        }
                    },
                    {
                        "node": {
                            "followed_by_viewer": false,
                            "full_name": "Bianca Somer Turkmen",
                            "username": "biancasomer",
                            "requested_by_viewer": false,
                            "is_verified": false,
                            "id": "465789422",
                            "profile_pic_url": "https://scontent-icn1-1.cdninstagram.com/t51.2885-19/s150x150/11376184_123717011297833_1428417928_a.jpg"
                        }
                    },
                    {
                        "node": {
                            "followed_by_viewer": false,
                            "full_name": "Princesse Mila \ud83d\udc51",
                            "username": "milaamore_",
                            "requested_by_viewer": false,
                            "is_verified": false,
                            "id": "1770291136",
                            "profile_pic_url": "https://scontent-icn1-1.cdninstagram.com/t51.2885-19/s150x150/18444023_214232412416253_3820715847534510080_a.jpg"
                        }
                    },
                    {
                        "node": {
                            "followed_by_viewer": false,
                            "full_name": "Elena Shumilova",
                            "username": "elena_shumilova",
                            "requested_by_viewer": false,
                            "is_verified": false,
                            "id": "1422511527",
                            "profile_pic_url": "https://scontent-icn1-1.cdninstagram.com/t51.2885-19/s150x150/17819216_1247936931990508_4810575117702660096_a.jpg"
                        }
                    },
                    {
                        "node": {
                            "followed_by_viewer": false,
                            "full_name": "\ud83c\udf54SARAH STAGE \ud83c\udf54",
                            "username": "sarahstage",
                            "requested_by_viewer": false,
                            "is_verified": true,
                            "id": "13958275",
                            "profile_pic_url": "https://scontent-icn1-1.cdninstagram.com/t51.2885-19/s150x150/12093792_997759863578333_262425643_a.jpg"
                        }
                    },
                    {
                        "node": {
                            "followed_by_viewer": false,
                            "full_name": "Man Explore",
                            "username": "man.explore",
                            "requested_by_viewer": false,
                            "is_verified": false,
                            "id": "3443043744",
                            "profile_pic_url": "https://scontent-icn1-1.cdninstagram.com/t51.2885-19/s150x150/14350645_685317181620974_1726546843_a.jpg"
                        }
                    },
                    {
                        "node": {
                            "followed_by_viewer": false,
                            "full_name": "",
                            "username": "kids_fashion_blogger",
                            "requested_by_viewer": false,
                            "is_verified": false,
                            "id": "1905903642",
                            "profile_pic_url": "https://scontent-icn1-1.cdninstagram.com/t51.2885-19/s150x150/11335150_1623465641262144_1114177545_a.jpg"
                        }
                    },
                    {
                        "node": {
                            "followed_by_viewer": false,
                            "full_name": "iNFLUMONSTER",
                            "username": "influmonster",
                            "requested_by_viewer": false,
                            "is_verified": false,
                            "id": "3053397824",
                            "profile_pic_url": "https://scontent-icn1-1.cdninstagram.com/t51.2885-19/s150x150/14350512_1643276205963404_6361167227634319360_a.jpg"
                        }
                    },
                    {
                        "node": {
                            "followed_by_viewer": false,
                            "full_name": "Luisa G. Due\u00f1as",
                            "username": "luisitastyle",
                            "requested_by_viewer": false,
                            "is_verified": false,
                            "id": "1753103569",
                            "profile_pic_url": "https://scontent-icn1-1.cdninstagram.com/t51.2885-19/s150x150/18579834_1434005046665556_8875881205191409664_a.jpg"
                        }
                    }
                ],
                "count": 669
            }
        }
    },
    "status": "ok"
}